firebird/butler/__about__.py
firebird/butler/__init__.py
firebird/butler/fbdp_pb2.py
firebird/butler/fbdp_pb2.pyi
firebird/butler/fbsd_pb2.py
firebird/butler/fbsd_pb2.pyi
firebird/butler/fbsp_pb2.py
firebird/butler/fbsp_pb2.pyi
firebird_butler_protobuf-2.0.0.dist-info/METADATA
firebird_butler_protobuf-2.0.0.dist-info/WHEEL
firebird_butler_protobuf-2.0.0.dist-info/entry_points.txt
firebird_butler_protobuf-2.0.0.dist-info/licenses/LICENSE
firebird_butler_protobuf-2.0.0.dist-info/RECORD
