Metadata-Version: 2.4
Name: firebird-butler-protobuf
Version: 2.0.0
Summary: Firebird Butler protocol buffers
Project-URL: Home, https://firebirdsql.org/en/firebird-butler-dev/
Project-URL: Documentation, https://firebird-butler.rtfd.io
Project-URL: Issues, https://github.com/FirebirdSQL/Butler/issues
Project-URL: Funding, https://github.com/sponsors/pcisar
Project-URL: Source, https://github.com/FirebirdSQL/Butler/python
Author-email: Pavel Cisar <pcisar@users.sourceforge.net>
License: MIT License
License-File: LICENSE
Keywords: Butler,Firebird,protobuf
Classifier: Development Status :: 5 - Production/Stable
Classifier: Intended Audience :: Developers
Classifier: License :: OSI Approved :: MIT License
Classifier: Operating System :: MacOS
Classifier: Operating System :: Microsoft :: Windows
Classifier: Operating System :: POSIX :: Linux
Classifier: Programming Language :: Python :: 3 :: Only
Classifier: Programming Language :: Python :: 3.11
Classifier: Programming Language :: Python :: 3.12
Classifier: Programming Language :: Python :: 3.13
Classifier: Topic :: Software Development
Requires-Python: >=3.11
Requires-Dist: protobuf~=5.29
